{
  "ImportImageTasks": [
    {
      "Architecture": "x86_64",
      "Description": "CPTC VM Import adcs",
      "ImageId": "ami-0afd33cfe9c8e0d66",
      "ImportTaskId": "import-ami-0cbfcc5f36f2cd85c",
      "LicenseType": "AWS",
      "Platform": "Windows",
      "SnapshotDetails": [
        {
          "Description": "CPTC VM Import adcs",
          "DeviceName": "/dev/sda1",
          "DiskImageSize": 53687091200.0,
          "Format": "RAW",
          "SnapshotId": "snap-0ea309d076d79a63b",
          "Status": "completed",
          "UserBucket": { "S3Bucket": "cptc-vms", "S3Key": "cptc-adcs.raw" }
        }
      ],
      "Status": "completed",
      "Tags": [{ "Key": "Name", "Value": "CPTC VM adcs" }],
      "BootMode": "legacy_bios"
    },
    {
      "Architecture": "x86_64",
      "Description": "CPTC VM Import dc01",
      "ImageId": "ami-07b4273f227541bff",
      "ImportTaskId": "import-ami-00d057fec5a8e931f",
      "LicenseType": "AWS",
      "Platform": "Windows",
      "SnapshotDetails": [
        {
          "Description": "CPTC VM Import dc01",
          "DeviceName": "/dev/sda1",
          "DiskImageSize": 53687091200.0,
          "Format": "RAW",
          "SnapshotId": "snap-0f10137e0fb2609c4",
          "Status": "completed",
          "UserBucket": { "S3Bucket": "cptc-vms", "S3Key": "cptc-dc01.raw" }
        }
      ],
      "Status": "completed",
      "Tags": [{ "Key": "Name", "Value": "CPTC VM dc01" }],
      "BootMode": "legacy_bios"
    },
    {
      "Architecture": "x86_64",
      "Description": "CPTC VM Import doapi",
      "ImageId": "ami-048984f8389164a46",
      "ImportTaskId": "import-ami-02c5eea4a49fdc04c",
      "LicenseType": "BYOL",
      "Platform": "Linux",
      "SnapshotDetails": [
        {
          "Description": "CPTC VM Import doapi",
          "DeviceName": "/dev/sda1",
          "DiskImageSize": 53687091200.0,
          "Format": "RAW",
          "SnapshotId": "snap-07fb06a1de9ff5053",
          "Status": "completed",
          "UserBucket": { "S3Bucket": "cptc-vms", "S3Key": "cptc-doapi.raw" }
        }
      ],
      "Status": "completed",
      "Tags": [{ "Key": "Name", "Value": "CPTC VM doapi" }],
      "BootMode": "legacy_bios"
    },
    {
      "Architecture": "x86_64",
      "Description": "CPTC VM Import hms",
      "ImageId": "ami-0647b402e25fb70f8",
      "ImportTaskId": "import-ami-05d7d55c3c16543e6",
      "LicenseType": "AWS",
      "Platform": "Windows",
      "SnapshotDetails": [
        {
          "Description": "CPTC VM Import hms",
          "DeviceName": "/dev/sda1",
          "DiskImageSize": 53687091200.0,
          "Format": "RAW",
          "SnapshotId": "snap-03328cec601ad175c",
          "Status": "completed",
          "UserBucket": { "S3Bucket": "cptc-vms", "S3Key": "cptc-hms.raw" }
        }
      ],
      "Status": "completed",
      "Tags": [{ "Key": "Name", "Value": "CPTC VM hms" }],
      "BootMode": "legacy_bios"
    },
    {
      "Architecture": "x86_64",
      "Description": "CPTC VM Import kiosk01",
      "ImageId": "ami-096a2e1a6ec5012ba",
      "ImportTaskId": "import-ami-0ee67218bb854f95b",
      "LicenseType": "AWS",
      "Platform": "Windows",
      "SnapshotDetails": [
        {
          "Description": "CPTC VM Import kiosk01",
          "DeviceName": "/dev/sda1",
          "DiskImageSize": 53687091200.0,
          "Format": "RAW",
          "SnapshotId": "snap-0d8502cfc3a91c5f8",
          "Status": "completed",
          "UserBucket": { "S3Bucket": "cptc-vms", "S3Key": "cptc-kiosk01.raw" }
        }
      ],
      "Status": "completed",
      "Tags": [{ "Key": "Name", "Value": "CPTC VM kiosk01" }],
      "BootMode": "legacy_bios"
    },
    {
      "Architecture": "x86_64",
      "Description": "CPTC VM Import kiosk02",
      "ImageId": "ami-028daabcea4a77fb0",
      "ImportTaskId": "import-ami-00449163c3fc7cb8b",
      "LicenseType": "AWS",
      "Platform": "Windows",
      "SnapshotDetails": [
        {
          "Description": "CPTC VM Import kiosk02",
          "DeviceName": "/dev/sda1",
          "DiskImageSize": 53687091200.0,
          "Format": "RAW",
          "SnapshotId": "snap-05defc3c8d0935fc0",
          "Status": "completed",
          "UserBucket": { "S3Bucket": "cptc-vms", "S3Key": "cptc-kiosk02.raw" }
        }
      ],
      "Status": "completed",
      "Tags": [{ "Key": "Name", "Value": "CPTC VM kiosk02" }],
      "BootMode": "legacy_bios"
    },
    {
      "Architecture": "x86_64",
      "Description": "CPTC VM Import kiosk03",
      "ImageId": "ami-03c6ed7ccfc973cab",
      "ImportTaskId": "import-ami-0b3687b158434b63e",
      "LicenseType": "AWS",
      "Platform": "Windows",
      "SnapshotDetails": [
        {
          "Description": "CPTC VM Import kiosk03",
          "DeviceName": "/dev/sda1",
          "DiskImageSize": 53687091200.0,
          "Format": "RAW",
          "SnapshotId": "snap-0fdd10f9b83be78a3",
          "Status": "completed",
          "UserBucket": { "S3Bucket": "cptc-vms", "S3Key": "cptc-kiosk03.raw" }
        }
      ],
      "Status": "completed",
      "Tags": [{ "Key": "Name", "Value": "CPTC VM kiosk03" }],
      "BootMode": "legacy_bios"
    },
    {
      "Architecture": "x86_64",
      "Description": "CPTC VM Import kiosk04",
      "ImageId": "ami-003c78bb7e40a15c1",
      "ImportTaskId": "import-ami-0c08c12df5d948e1f",
      "LicenseType": "AWS",
      "Platform": "Windows",
      "SnapshotDetails": [
        {
          "Description": "CPTC VM Import kiosk04",
          "DeviceName": "/dev/sda1",
          "DiskImageSize": 53687091200.0,
          "Format": "RAW",
          "SnapshotId": "snap-04c7cfc3ba8cbcb6c",
          "Status": "completed",
          "UserBucket": { "S3Bucket": "cptc-vms", "S3Key": "cptc-kiosk04.raw" }
        }
      ],
      "Status": "completed",
      "Tags": [{ "Key": "Name", "Value": "CPTC VM kiosk04" }],
      "BootMode": "legacy_bios"
    },
    {
      "Architecture": "x86_64",
      "Description": "CPTC VM Import ldap",
      "ImageId": "ami-0c19ed51243876940",
      "ImportTaskId": "import-ami-06293b32f70c0b7bb",
      "LicenseType": "BYOL",
      "Platform": "Linux",
      "SnapshotDetails": [
        {
          "Description": "CPTC VM Import ldap",
          "DeviceName": "/dev/sda1",
          "DiskImageSize": 53687091200.0,
          "Format": "RAW",
          "SnapshotId": "snap-031ddcca2803b7d79",
          "Status": "completed",
          "UserBucket": { "S3Bucket": "cptc-vms", "S3Key": "cptc-ldap.raw" }
        }
      ],
      "Status": "completed",
      "Tags": [{ "Key": "Name", "Value": "CPTC VM ldap" }],
      "BootMode": "legacy_bios"
    },
    {
      "Architecture": "x86_64",
      "Description": "CPTC VM Import lps",
      "ImageId": "ami-0eedc80277d2ebed7",
      "ImportTaskId": "import-ami-0a9000656f5d014c3",
      "LicenseType": "BYOL",
      "Platform": "Linux",
      "SnapshotDetails": [
        {
          "Description": "CPTC VM Import lps",
          "DeviceName": "/dev/sda1",
          "DiskImageSize": 53687091200.0,
          "Format": "RAW",
          "SnapshotId": "snap-0f888721c4ec7af60",
          "Status": "completed",
          "UserBucket": { "S3Bucket": "cptc-vms", "S3Key": "cptc-lps.raw" }
        }
      ],
      "Status": "completed",
      "Tags": [{ "Key": "Name", "Value": "CPTC VM lps" }],
      "BootMode": "legacy_bios"
    },
    {
      "Architecture": "x86_64",
      "Description": "CPTC VM Import media",
      "ImageId": "ami-0b82130d627462610",
      "ImportTaskId": "import-ami-0570a4e7eee09a453",
      "LicenseType": "BYOL",
      "Platform": "Linux",
      "SnapshotDetails": [
        {
          "Description": "CPTC VM Import media",
          "DeviceName": "/dev/sda1",
          "DiskImageSize": 53687091200.0,
          "Format": "RAW",
          "SnapshotId": "snap-01f78ad44da7575ec",
          "Status": "completed",
          "UserBucket": { "S3Bucket": "cptc-vms", "S3Key": "cptc-media.raw" }
        }
      ],
      "Status": "completed",
      "Tags": [{ "Key": "Name", "Value": "CPTC VM media" }],
      "BootMode": "legacy_bios"
    },
    {
      "Architecture": "x86_64",
      "Description": "CPTC VM Import payment-db",
      "ImageId": "ami-066f4ab32f25eb25a",
      "ImportTaskId": "import-ami-0a370690ea1daf062",
      "LicenseType": "BYOL",
      "Platform": "Linux",
      "SnapshotDetails": [
        {
          "Description": "CPTC VM Import payment-db",
          "DeviceName": "/dev/sda1",
          "DiskImageSize": 53687091200.0,
          "Format": "RAW",
          "SnapshotId": "snap-07ccbe4f4d766d035",
          "Status": "completed",
          "UserBucket": {
            "S3Bucket": "cptc-vms",
            "S3Key": "cptc-payment-db.raw"
          }
        }
      ],
      "Status": "completed",
      "Tags": [{ "Key": "Name", "Value": "CPTC VM payment-db" }],
      "BootMode": "legacy_bios"
    },
    {
      "Architecture": "x86_64",
      "Description": "CPTC VM Import payment-web",
      "ImageId": "ami-0abd54cb19c657249",
      "ImportTaskId": "import-ami-02a533ae9f3cbb3e0",
      "LicenseType": "BYOL",
      "Platform": "Linux",
      "SnapshotDetails": [
        {
          "Description": "CPTC VM Import payment-web",
          "DeviceName": "/dev/sda1",
          "DiskImageSize": 53687091200.0,
          "Format": "RAW",
          "SnapshotId": "snap-0aff5299dd4c1b044",
          "Status": "completed",
          "UserBucket": {
            "S3Bucket": "cptc-vms",
            "S3Key": "cptc-payment-web.raw"
          }
        }
      ],
      "Status": "completed",
      "Tags": [{ "Key": "Name", "Value": "CPTC VM payment-web" }],
      "BootMode": "legacy_bios"
    },
    {
      "Architecture": "x86_64",
      "Description": "CPTC VM Import profiler",
      "ImageId": "ami-0d6ca849652e4ebf3",
      "ImportTaskId": "import-ami-01ab6d294c050ea95",
      "LicenseType": "BYOL",
      "Platform": "Linux",
      "SnapshotDetails": [
        {
          "Description": "CPTC VM Import profiler",
          "DeviceName": "/dev/sda1",
          "DiskImageSize": 53687091200.0,
          "Format": "RAW",
          "SnapshotId": "snap-09e2825f2073006f2",
          "Status": "completed",
          "UserBucket": { "S3Bucket": "cptc-vms", "S3Key": "cptc-profiler.raw" }
        }
      ],
      "Status": "completed",
      "Tags": [{ "Key": "Name", "Value": "CPTC VM profiler" }],
      "BootMode": "legacy_bios"
    },
    {
      "Architecture": "x86_64",
      "Description": "CPTC VM Import workstation01",
      "ImageId": "ami-09efdff5e7caf7139",
      "ImportTaskId": "import-ami-0b00af9303f9caaf9",
      "LicenseType": "AWS",
      "Platform": "Windows",
      "SnapshotDetails": [
        {
          "Description": "CPTC VM Import workstation01",
          "DeviceName": "/dev/sda1",
          "DiskImageSize": 53687091200.0,
          "Format": "RAW",
          "SnapshotId": "snap-0c0b5b85ba6c59ba3",
          "Status": "completed",
          "UserBucket": {
            "S3Bucket": "cptc-vms",
            "S3Key": "cptc-workstation01.raw"
          }
        }
      ],
      "Status": "completed",
      "Tags": [{ "Key": "Name", "Value": "CPTC VM workstation01" }],
      "BootMode": "legacy_bios"
    },
    {
      "Architecture": "x86_64",
      "Description": "CPTC VM Import workstation02",
      "ImageId": "ami-026d4e538685ce775",
      "ImportTaskId": "import-ami-0f376f13e147c70e3",
      "LicenseType": "AWS",
      "Platform": "Windows",
      "SnapshotDetails": [
        {
          "Description": "CPTC VM Import workstation02",
          "DeviceName": "/dev/sda1",
          "DiskImageSize": 53687091200.0,
          "Format": "RAW",
          "SnapshotId": "snap-093138f2c332711a3",
          "Status": "completed",
          "UserBucket": {
            "S3Bucket": "cptc-vms",
            "S3Key": "cptc-workstation02.raw"
          }
        }
      ],
      "Status": "completed",
      "Tags": [{ "Key": "Name", "Value": "CPTC VM workstation02" }],
      "BootMode": "legacy_bios"
    }
  ],
  "ResponseMetadata": {
    "RequestId": "6b1ea3f5-f71c-4b37-835c-9e07762782ec",
    "HTTPStatusCode": 200,
    "HTTPHeaders": {
      "x-amzn-requestid": "6b1ea3f5-f71c-4b37-835c-9e07762782ec",
      "cache-control": "no-cache, no-store",
      "strict-transport-security": "max-age=31536000; includeSubDomains",
      "vary": "accept-encoding",
      "content-type": "text/xml;charset=UTF-8",
      "transfer-encoding": "chunked",
      "date": "Mon, 25 Sep 2023 16:10:00 GMT",
      "server": "AmazonEC2"
    },
    "RetryAttempts": 0
  }
}
